gemseo_pdfo/__init__.py
gemseo_pdfo/pdfo.py
gemseo_pdfo/settings/__init__.py
gemseo_pdfo/settings/base_pdfo_settings.py
gemseo_pdfo/settings/pdfo_bobyqa_settings.py
gemseo_pdfo/settings/pdfo_cobyla_settings.py
gemseo_pdfo/settings/pdfo_newuoa_settings.py
gemseo_pdfo-2.0.3.dist-info/licenses/LICENSE.txt
gemseo_pdfo-2.0.3.dist-info/METADATA
gemseo_pdfo-2.0.3.dist-info/WHEEL
gemseo_pdfo-2.0.3.dist-info/entry_points.txt
gemseo_pdfo-2.0.3.dist-info/top_level.txt
gemseo_pdfo-2.0.3.dist-info/RECORD
