Metadata-Version: 2.4
Name: gemseo-pdfo
Version: 2.0.3
Summary: PDFO wrapper for GEMSEO
Author-email: GEMSEO developers <contact@gemseo.org>
License-Expression: LGPL-3.0
Project-URL: Homepage, https://gemseo.org
Project-URL: Source, https://gitlab.com/gemseo/dev/gemseo-pdfo
Project-URL: Issues, https://gitlab.com/gemseo/dev/gemseo-pdfo/-/issues
Classifier: Intended Audience :: Science/Research
Classifier: Topic :: Scientific/Engineering
Classifier: Operating System :: POSIX :: Linux
Classifier: Operating System :: MacOS
Classifier: Operating System :: Microsoft :: Windows
Classifier: Programming Language :: Python :: 3 :: Only
Classifier: Programming Language :: Python :: 3.10
Classifier: Programming Language :: Python :: 3.11
Classifier: Programming Language :: Python :: 3.12
Requires-Python: <3.13,>=3.10
License-File: LICENSE.txt
Requires-Dist: gemseo[all]<7,>=6.3
Requires-Dist: numpy<2
Requires-Dist: pdfo<=2.2.0,>=1.0.0
Dynamic: license-file
